odoo10_addon_pos_stock_picking_invoice_link-10.0.1.0.0-py2.7-nspkg.pth
odoo/addons/pos_stock_picking_invoice_link/README.rst
odoo/addons/pos_stock_picking_invoice_link/__init__.py
odoo/addons/pos_stock_picking_invoice_link/__manifest__.py
odoo/addons/pos_stock_picking_invoice_link/models/__init__.py
odoo/addons/pos_stock_picking_invoice_link/models/pos_order.py
odoo/addons/pos_stock_picking_invoice_link/static/description/icon.png
odoo/addons/pos_stock_picking_invoice_link/tests/__init__.py
odoo/addons/pos_stock_picking_invoice_link/tests/test_point_of_sale_stock_invoice_link.py
odoo10_addon_pos_stock_picking_invoice_link-10.0.1.0.0.dist-info/DESCRIPTION.rst
odoo10_addon_pos_stock_picking_invoice_link-10.0.1.0.0.dist-info/METADATA
odoo10_addon_pos_stock_picking_invoice_link-10.0.1.0.0.dist-info/RECORD
odoo10_addon_pos_stock_picking_invoice_link-10.0.1.0.0.dist-info/WHEEL
odoo10_addon_pos_stock_picking_invoice_link-10.0.1.0.0.dist-info/metadata.json
odoo10_addon_pos_stock_picking_invoice_link-10.0.1.0.0.dist-info/namespace_packages.txt
odoo10_addon_pos_stock_picking_invoice_link-10.0.1.0.0.dist-info/top_level.txt
